yaoys_checkin/AutoCheckIn.py
yaoys_checkin/AutoCheckinService.py
yaoys_checkin/__init__.py
yaoys_checkin/__version__.py
yaoys_checkin/ablesci_checkin/__init__.py
yaoys_checkin/ablesci_checkin/ableSci_checkin.py
yaoys_checkin/aliyunpan_checkin/__init__.py
yaoys_checkin/aliyunpan_checkin/aliyunpan_checkin.py
yaoys_checkin/bilibili_checkin/__init__.py
yaoys_checkin/bilibili_checkin/bilibili_alive_auto_checkin.py
yaoys_checkin/bilibili_checkin/bilibili_auto_checkin.py
yaoys_checkin/checkin_util/__init__.py
yaoys_checkin/checkin_util/check_version_util.py
yaoys_checkin/checkin_util/checkin_class.py
yaoys_checkin/checkin_util/checkin_log.py
yaoys_checkin/checkin_util/common_util.py
yaoys_checkin/checkin_util/constants.py
yaoys_checkin/checkin_util/logutil.py
yaoys_checkin/checkin_util/uc_driver.py
yaoys_checkin/cloud_189_checkin/1.py
yaoys_checkin/cloud_189_checkin/__init__.py
yaoys_checkin/cloud_189_checkin/cloud189_checkin.py
yaoys_checkin/glados_checkin/__init__.py
yaoys_checkin/glados_checkin/glados.py
yaoys_checkin/gufenxueshu_checkin/__init__.py
yaoys_checkin/gufenxueshu_checkin/gufen_checkin.py
yaoys_checkin/jiaoyimao/__init__.py
yaoys_checkin/jiaoyimao/jiaoyimao_checkin.py
yaoys_checkin/model/__init__.py
yaoys_checkin/model/all_class_parent.py
yaoys_checkin/piaoyunge/__init__.py
yaoys_checkin/piaoyunge/piaoyunge_checkin.py
yaoys_checkin/piaoyunge/piaoyunge_checkin_1.py
yaoys_checkin/piaoyunge/piaoyunge_checkin_获取fromhash.py
yaoys_checkin/piaoyunge/解析xml.py
yaoys_checkin/push_message/__init__.py
yaoys_checkin/push_message/push_message.py
yaoys_checkin/tieba_checkin/__init__.py
yaoys_checkin/tieba_checkin/tieba_checkin.py
yaoys_checkin/wps_checkin/__init__.py
yaoys_checkin/wps_checkin/wps_cloud_checkin.py
yaoys_checkin/wps_checkin/wps_vip_checkin.py
yaoys_checkin/wuaipojie_checkin/__init__.py
yaoys_checkin/wuaipojie_checkin/wuaipojie.py
yaoys_checkin/xiaoheihe/__init__.py
yaoys_checkin/xiaoheihe/xiaoheihe_checkin.py
yaoys_checkin-0.1.9.dist-info/LICENSE
yaoys_checkin-0.1.9.dist-info/METADATA
yaoys_checkin-0.1.9.dist-info/WHEEL
yaoys_checkin-0.1.9.dist-info/entry_points.txt
yaoys_checkin-0.1.9.dist-info/top_level.txt
yaoys_checkin-0.1.9.dist-info/RECORD
